autogenbench/__init__.py
autogenbench/__main__.py
autogenbench/cli.py
autogenbench/clone_cmd.py
autogenbench/load_module.py
autogenbench/run_cmd.py
autogenbench/tabulate_cmd.py
autogenbench/version.py
autogenbench/res/Dockerfile
autogenbench/template/global_finalize.sh
autogenbench/template/global_init.sh
autogenbench/template/requirements.txt
autogenbench/template/testbed_utils.py
autogenbench-0.0.3.dist-info/METADATA
autogenbench-0.0.3.dist-info/WHEEL
autogenbench-0.0.3.dist-info/entry_points.txt
autogenbench-0.0.3.dist-info/top_level.txt
autogenbench-0.0.3.dist-info/RECORD
