Metadata-Version: 2.1
Name: autogenbench
Version: 0.0.3
Summary: AutoGen Testbed Tools
Author-email: Autogen Team <auto-gen@outlook.com>
Project-URL: Homepage, https://github.com/microsoft/autogen
Project-URL: Bug Tracker, https://github.com/microsoft/autogen/issues
Classifier: Programming Language :: Python :: 3
Classifier: License :: OSI Approved :: MIT License
Classifier: Operating System :: OS Independent
Requires-Python: <3.13,>=3.8
Requires-Dist: pyautogen
Requires-Dist: docker
Requires-Dist: huggingface-hub
Requires-Dist: tabulate
